{"type":null,"faqId":14195,"title":"What video formats and sizes do cameras support?","answer":"<span><span>Cameras of your phone can record videos in mp4, HD (720P), VGA (640 x 480), QVGA (320 x 240), and MMS (176x144) formats. The size of videos you can record depends on the free space of your phone memory.</span></span></a>","faqTypeId":null,"faqType":null,"useful":0,"unUseful":0,"languageId":242,"languageName":"id","faqCode":"5941","faqTypeCode":null,"isTop":"0","moduleCode":"faq","productId":null,"productCode":null,"postDate":1407301163000,"seriesProductName":"G6-U10","visitedTimes":3,"isUsefulFlag":null,"score":0,"times":0,"imageList":null,"displayType":"text","justView":"0","fileName":null,"filePath":null,"imagePath":null,"imageName":null,"productIdList":null,"curPage":null,"pageSize":null,"siteCode":null,"statusFlag":"Publish","returnCode":0,"totalRows":null,"keywords":"video format","avgScore":0.0,"createDate":null,"totalPages":null}