{"type":null,"faqId":15395,"title":"榮耀X1(7D-503LT,7D-501L,7D-503L,7D-501U)_可以註冊4G網路，但無法撥通電話的問題","answer":"<p style=\"MARGIN: 0cm 0cm 0pt; FONT-FAMILY: 'Calibri','sans-serif'; FONT-SIZE: 12pt\"><span style=\"FONT-FAMILY: 'PMingLiU','serif'\">原因：因運營商限制在僅<span>4G</span>模式下是無法進行語音通話的，系統預設的是<span>4G</span>優先模式可以接打電話，請不要在設置中（設置<span>--&gt;</span>移動網路設置<span>---&gt;</span>網路模式設置<span>---&gt;</span>僅<span>4G</span>模式）中選擇<span>“</span>僅<span>4G”</span>模式。處理方式：<span>1</span>） 請更改設置（設置<span>--&gt;</span>移動網路設置<span>---&gt;</span>網路模式設置），修改為<span>4G</span>優先（<span>4G/3G/2G</span>）模式。</span></p>","faqTypeId":null,"faqType":null,"useful":1,"unUseful":2,"languageId":201,"languageName":"tr_CN","faqCode":"7713","faqTypeCode":null,"isTop":"0","moduleCode":"faq","productId":null,"productCode":null,"postDate":1412671940000,"seriesProductName":"7D-501L,7D-501u","visitedTimes":581,"isUsefulFlag":null,"score":0,"times":0,"imageList":null,"displayType":"text","justView":"0","fileName":null,"filePath":null,"imagePath":null,"imageName":null,"productIdList":null,"curPage":null,"pageSize":null,"siteCode":null,"statusFlag":"Publish","returnCode":0,"totalRows":null,"keywords":"7D-501L,7D-501u,X13G,X14G,X1","avgScore":0.0,"createDate":null,"totalPages":null}