{"type":null,"faqId":17641,"title":"荣耀6Plus金卡服务与MATE7有什么区别？","answer":"<p>主要区别在于：\n<br>\n1. 礼包内容不同；\n<br>\n2. Mate7有赠送碎屏险，荣耀6 Plus没有。<br>\n</p>","faqTypeId":144,"faqType":"其他","useful":0,"unUseful":1,"languageId":2,"languageName":"zh_cn","faqCode":"402","faqTypeCode":"Handsets-Others","isTop":"0","moduleCode":"faq","productId":null,"productCode":null,"postDate":1419559191000,"seriesProductName":"Pine-TL10,Pine-TL20,Pine-UL00","visitedTimes":1365,"isUsefulFlag":null,"score":15,"times":5,"imageList":null,"displayType":"text","justView":"0","fileName":null,"filePath":null,"imagePath":null,"imageName":null,"productIdList":null,"curPage":null,"pageSize":null,"siteCode":null,"statusFlag":"Publish","returnCode":0,"totalRows":null,"keywords":"荣耀6Plus，金卡，MATE7，区别，金卡，服务","avgScore":3.0,"createDate":null,"totalPages":null}