{"type":null,"faqId":21653,"title":"如何清洁手环？","answer":"<html>\n<head>\n<META http-equiv=\"Content-Type\" content=\"text/html; charset=UTF-8\">\n<style type=\"text/css\">.b1{white-space-collapsing:preserve;}\n.d1{margin: 0.9111111in 1.25in 1.0in 1.25in;}\n.p1{text-indent:0.29166666in;text-align:start;hyphenate:auto;font-family:微软雅黑;font-size:12pt;}\n.p2{text-indent:0.008333334in;margin-left:0.29166666in;text-align:start;hyphenate:auto;font-family:微软雅黑;font-size:12pt;}\n.p3{text-indent:0.29166666in;margin-left:0.59166664in;text-align:start;hyphenate:auto;font-family:微软雅黑;font-size:12pt;}\n.s1{display: inline-block; text-indent: 0; min-width: 0.10277778in;}\n</style>\n</head>\n<body class=\"b1\">\n<div  >\n<p  >\n<span>您可以用沾水的纸巾或湿布清洁手环，然后使用干布或干纸巾彻底擦干。</span>\n</p>\n<p  >\n<span>清洁过程中需要注意以下几点：</span>\n</p>\n<p  >\n <span>请勿添加化学洗涤用品。</span>\n</p>\n<p  >\n <span>蓝牙耳机与腕带分开单独清洁，切勿长时间浸泡。</span>\n</p>\n<p  >\n <span>请留意MIC孔和耳机孔是否有水珠残留，残留水珠可能影响耳机通话质量，您可以用纸巾吸干水珠。</span>\n</p>\n</div>\n</body>\n</html>\n","faqTypeId":212,"faqType":"其他","useful":0,"unUseful":0,"languageId":2,"languageName":"zh_cn","faqCode":"5354","faqTypeCode":"Wearable_Device-Others","isTop":"0","moduleCode":"faq","productId":null,"productCode":null,"postDate":1427334706000,"seriesProductName":"B1-Honor","visitedTimes":71,"isUsefulFlag":null,"score":0,"times":0,"imageList":null,"displayType":"text","justView":"0","fileName":null,"filePath":null,"imagePath":null,"imageName":null,"productIdList":null,"curPage":null,"pageSize":null,"siteCode":null,"statusFlag":"Publish","returnCode":0,"totalRows":null,"keywords":null,"avgScore":0.0,"createDate":null,"totalPages":null}