{"type":null,"faqId":34524,"title":" Developer Options","answer":"<html>\n<head>\n<META http-equiv=\"Content-Type\" content=\"text/html; charset=UTF-8\">\n<style type=\"text/css\">.b1{white-space-collapsing:preserve;}\n.d1{margin: 1.18125in 0.7875in 1.18125in 0.7875in;}\n.s1{font-weight:bold;}\n.p1{margin-left:0.8784722in;margin-top:0.055555556in;margin-bottom:0.055555556in;text-align:start;hyphenate:auto;font-family:Arial;font-size:10pt;}\n</style>\n</head>\n<body class=\"b1\">\n<div  >\n<p  >\n<span>Users can </span><span class=\"s1\">enable / disable </span><span>the developer options via the touch switch.</span>\n</p>\n<p  >\n<span>1. USB debugging: Used to enable the debug mode, by which you can debug a mobile phone with the adb command</span>\n</p>\n<p  >\n<span>2. Keep Awake: Used to prevent the screen from sleeping when charging</span>\n</p>\n<p  >\n<span>3. Allow mock location: Used to enable the mock location function</span>\n</p>\n<p  >\n<span>4. Desktop backup password: Used to set the backup password</span>\n</p>\n<p  >\n<span>5. Pointer location: Used to display the current touch data when you touch the screen</span>\n</p>\n<p  >\n<span>6. Display touch operation: Used to provide visual prompt for touch operation</span>\n</p>\n<p  >\n<span>7. Display the CPU usage: Used to display the usage of the current system CPU</span>\n</p>\n<p  >\n<span>8. Force GPU rendering: Used for acceleration with 2D hardware in applications</span>\n</p>\n<p  >\n<span>9. Animation zooming: Used to control the zooming speed</span>\n</p>\n<p  >\n<span>10. Background process limit: Used to limit the number of background processes</span>\n</p>\n<p  >\n<span>11. Display all \"Applications are unresponsive\": Used to display the \"Application is unresponsive\" dialog box for background applications.</span>\n</p>\n</div>\n</body>\n</html>\n","faqTypeId":null,"faqType":null,"useful":0,"unUseful":0,"languageId":244,"languageName":"mm","faqCode":"9265","faqTypeCode":null,"isTop":"0","moduleCode":"faq","productId":null,"productCode":null,"postDate":1436866804000,"seriesProductName":"Y625-U32","visitedTimes":3,"isUsefulFlag":null,"score":0,"times":0,"imageList":null,"displayType":"text","justView":"0","fileName":null,"filePath":null,"imagePath":null,"imageName":null,"productIdList":null,"curPage":null,"pageSize":null,"siteCode":null,"statusFlag":"Publish","returnCode":0,"totalRows":null,"keywords":"Y625-U32, Ascend Y25","avgScore":0.0,"createDate":null,"totalPages":null}