{"type":null,"faqId":45601,"title":"【玩·P8max】华为P8max延时摄影操作指南","answer":"<p>时光静好，岁月安然，华为P8max延时摄影利用摄影技术将缓慢变化的过程快速播放，呈现出行云流水般的奇异精彩景象，为您献上一段动静相融的视觉盛宴。<br>\n</p>","faqTypeId":1086,"faqType":"相机与图库","useful":0,"unUseful":0,"languageId":2,"languageName":"zh_cn","faqCode":"1181","faqTypeCode":"Handsets-Camera-Gallery","isTop":"0","moduleCode":"faq","productId":null,"productCode":null,"postDate":1443060785000,"seriesProductName":"DAV-703L","visitedTimes":325,"isUsefulFlag":null,"score":0,"times":0,"imageList":null,"displayType":"video","justView":"0","fileName":"150924101254a.mp4","filePath":"http://consumer.huawei.com/resources/faq/video/150924101254a.mp4","imagePath":"http://consumer.huawei.com/resources/faq/images/150924101305a.jpg","imageName":"150924101305a.jpg","productIdList":null,"curPage":null,"pageSize":null,"siteCode":null,"statusFlag":"Publish","returnCode":0,"totalRows":null,"keywords":"如何使用延时摄影功能,怎样使用手机相机里的延时摄影,延时摄影是什么,延时摄影怎样使用","avgScore":0.0,"createDate":null,"totalPages":null}