{"type":null,"faqId":49786,"title":"华为智能手表_如何使用手腕手势？","answer":"<body style=\"clear:both; padding-left:10px; padding-top:5px; padding-right:5px; padding-bottom:5px\"><div id=\"body63847192\"><p id=\"ZH-CN_TOPIC_0022329169__p56517943\">在手表主界面向左滑动一下，选择 <strong id=\"ZH-CN_TOPIC_0022329169__b24204791181127\">设置</strong>，设置 <strong id=\"ZH-CN_TOPIC_0022329169__b23859639181118\">手腕手势</strong> 为 <strong id=\"ZH-CN_TOPIC_0022329169__b14511025181134\">开启</strong>，当您收到多条通知时，可以转动手腕切换通知。</p></div><div><div class=\"familylinks\"></div></div></body>","faqTypeId":721,"faqType":"软件与APP使用","useful":1,"unUseful":1,"languageId":2,"languageName":"zh_cn","faqCode":"zh-cn_topic_0022329169","faqTypeCode":"Wearable_Device-Software-Apps","isTop":"0","moduleCode":"faq","productId":null,"productCode":null,"postDate":1448605855000,"seriesProductName":"Mercury-G00,Mercury-G01,Mercury-G10","visitedTimes":51,"isUsefulFlag":null,"score":0,"times":0,"imageList":null,"displayType":"text","justView":"0","fileName":null,"filePath":null,"imagePath":null,"imageName":null,"productIdList":null,"curPage":null,"pageSize":null,"siteCode":null,"statusFlag":"Publish","returnCode":0,"totalRows":null,"keywords":"手腕手势","avgScore":0.0,"createDate":null,"totalPages":null}