{"type":null,"faqId":7165,"title":"手机QQ里边的聊天记录如何删除？","answer":"菜单中有个&ldquo;删除记录&rdquo;的图标，点击即可删除。","faqTypeId":null,"faqType":null,"useful":0,"unUseful":0,"languageId":2,"languageName":"zh_cn","faqCode":"7305","faqTypeCode":null,"isTop":"0","moduleCode":"faq","productId":null,"productCode":null,"postDate":1314264520000,"seriesProductName":"","visitedTimes":3225,"isUsefulFlag":null,"score":97,"times":32,"imageList":null,"displayType":"text","justView":"0","fileName":null,"filePath":null,"imagePath":null,"imageName":null,"productIdList":null,"curPage":null,"pageSize":null,"siteCode":null,"statusFlag":"Publish","returnCode":0,"totalRows":null,"keywords":null,"avgScore":3.0,"createDate":null,"totalPages":null}