{"type":null,"faqId":7315,"title":"为什么音乐空间的歌词下载有时会失败？","answer":"歌词下载失败的原因有以下两种可能：<br />①歌词下载的准确率取决于搜索关键字的准确率。如果歌词下载失败，用户可以修改歌曲名称提高下载准确率，修改文件名为如下形式：歌曲名称 + 空格 + 歌手名称，例如&ldquo;冰雨 刘德华&rdquo;。<br />②由于歌曲版权问题，歌词提供网站可能无法提供歌词下载，部分歌词也可能无法找到。","faqTypeId":null,"faqType":null,"useful":0,"unUseful":0,"languageId":2,"languageName":"zh_cn","faqCode":"7455","faqTypeCode":null,"isTop":"0","moduleCode":"faq","productId":null,"productCode":null,"postDate":1319773866000,"seriesProductName":"","visitedTimes":100,"isUsefulFlag":null,"score":0,"times":0,"imageList":null,"displayType":"text","justView":"0","fileName":null,"filePath":null,"imagePath":null,"imageName":null,"productIdList":null,"curPage":null,"pageSize":null,"siteCode":null,"statusFlag":"Publish","returnCode":0,"totalRows":null,"keywords":null,"avgScore":0.0,"createDate":null,"totalPages":null}