{
  "type": null,
  "faqId": 14534,
  "title": "Why does F255 call out so slow after my dialing?",
  "answer": " F255 will make sure your dialing-up is finished for 4 seconds. You also can press “#” key to call out at once.",
  "faqTypeId": null,
  "faqType": null,
  "useful": 0,
  "unUseful": 0,
  "languageId": 1,
  "languageName": "en",
  "faqCode": "6514",
  "faqTypeCode": null,
  "isTop": "0",
  "moduleCode": "faq",
  "productId": null,
  "productCode": null,
  "postDate": 1408743060000,
  "seriesProductName": "",
  "visitedTimes": 38,
  "isUsefulFlag": null,
  "score": 0,
  "times": 0,
  "imageList": null,
  "displayType": "text",
  "justView": "0",
  "fileName": null,
  "filePath": null,
  "imagePath": null,
  "imageName": null,
  "productIdList": null,
  "curPage": null,
  "pageSize": null,
  "siteCode": null,
  "statusFlag": "Publish",
  "returnCode": 0,
  "totalRows": null,
  "keywords": null,
  "avgScore": 0.0,
  "createDate": null,
  "totalPages": null
}