{
  "type": null,
  "faqId": 31058,
  "title": "How do I enable safe mode?",
  "answer": " When switching on the phone, press and hold the volume down button and the phone will enter safe mode. \r\n\r\n When the phone is switched on, if you press and hold the power button and select Power off in the displayed menu, the system will display a Reboot to safe mode dialog box. Touch OK to restart your phone and enter safe mode. \r\n\r\n After entering safe mode, a prompt will be displayed in the lower left corner of the screen. \r\n\r\n ![](http://consumer.huawei.com/support/servlet/imageServlet?dlType=HtmlAreaImage&imageId=97074)\r\n\r\n Some phone models do not support safe mode. \r\n\n\n\n\n",
  "faqTypeId": null,
  "faqType": null,
  "useful": 0,
  "unUseful": 0,
  "languageId": 1,
  "languageName": "en",
  "faqCode": "5578",
  "faqTypeCode": null,
  "isTop": "0",
  "moduleCode": "faq",
  "productId": null,
  "productCode": null,
  "postDate": 1434601295000,
  "seriesProductName": "EDGE-U00,G6-L11,G6-U10,G760-L01,Jazz-L09,Jazz-L11,Jazz-TL10,Sophia-L10,Y220-U00,Y221-U22,Y330-U11",
  "visitedTimes": 126,
  "isUsefulFlag": null,
  "score": 0,
  "times": 0,
  "imageList": null,
  "displayType": "text",
  "justView": "0",
  "fileName": null,
  "filePath": null,
  "imagePath": null,
  "imageName": null,
  "productIdList": null,
  "curPage": null,
  "pageSize": null,
  "siteCode": null,
  "statusFlag": "Publish",
  "returnCode": 0,
  "totalRows": null,
  "keywords": "enable safe mode, enter safe mode, safe mode",
  "avgScore": 0.0,
  "createDate": null,
  "totalPages": null
}