{
  "type": null,
  "faqId": 6308,
  "title": "How do I set my phone to vibrate or mute quickly?",
  "answer": "1、From the home screen or main menu screen (other than when you are playing multi-media files), press and hold the volume down button. The vibration mode follows the silent mode.  \r\n2、Touch Settings > Sound > Vibrate to set the phone to vibrate. To mute the phone, select Ringer Volume, which is on the same menu page as the Vibrate option, and then drag the volume bar all the way to the left.",
  "faqTypeId": null,
  "faqType": null,
  "useful": 1,
  "unUseful": 0,
  "languageId": 1,
  "languageName": "en",
  "faqCode": "6308",
  "faqTypeCode": null,
  "isTop": "0",
  "moduleCode": "faq",
  "productId": null,
  "productCode": null,
  "postDate": 1321336541000,
  "seriesProductName": "",
  "visitedTimes": 388,
  "isUsefulFlag": null,
  "score": 1,
  "times": 1,
  "imageList": null,
  "displayType": "text",
  "justView": "0",
  "fileName": null,
  "filePath": null,
  "imagePath": null,
  "imageName": null,
  "productIdList": null,
  "curPage": null,
  "pageSize": null,
  "siteCode": null,
  "statusFlag": "Publish",
  "returnCode": 0,
  "totalRows": null,
  "keywords": null,
  "avgScore": 1.0,
  "createDate": null,
  "totalPages": null
}