{
	"PutUrl" : "hwqna",
	"settings" : {
		"number_of_shards" : 1,
		"number_of_replicas" : 2
	},
	"mappings" : {
		"_default_" : {
			"properties" : {
				"FaqId" : {
					"type" : "long"
				},
				"Q_chinese_s" : {
					"type" : "string",
					"analyzer" : "smartcn",
					"fields" : {
						"autocomplete" : {
							"type" : "string",
							"analyzer" : "autocomplete"
						}
					}
				},
				"A_chinese_s" : {
					"type" : "string",
					"analyzer" : "smartcn",
					"fields" : {
						"autocomplete" : {
							"type" : "string",
							"analyzer" : "autocomplete"
						}
					}
				},
				"Type" : {
					"type" : "string",
					"analyzer" : "smartcn",
					"fields" : {
						"raw" : {
							"type" : "string",
							"index" : "not_analyzed"
						},
						"lowercaseraw" : {
							"type" : "string",
							"analyzer" : "lowercase_keyword"
						}
					}
				},
				"Language" : {
					"type" : "string",
					"fields" : {
						"lowercaseraw" : {
							"type" : "string",
							"analyzer" : "lowercase_keyword"
						}
					}
				},
				"Keywords" : {
					"type" : "string",
					"analyzer" : "smartcn"
				},
				"Url" : {
					"type" : "string",
					"fields" : {
						"lowercaseraw" : {
							"type" : "string",
							"analyzer" : "lowercase_keyword"
						}
					}
				},
				"LastModified" : {
					"type" : "date",
					"format" : "dateOptionalTime"
				}
			}
		}
	}
}
