{
  "type": null,
  "faqId": 10922,
  "title": "荣耀3C （H30-T10&H30-U10）  如何关闭和启用数据业务",
  "answer": " 关闭和开启数据业务的方法： \r\n\r\n l 选择**设置** > **移动网络 > ****启用数据流量**，打开/关闭关闭数据业务。 \r\n\r\n l 在下拉通知栏中打开数据业务： \r\n\r\n 从屏幕下拉通知栏，点击数据开关![](http://consumer.huawei.com/support/servlet/imageServlet?dlType=HtmlAreaImage&imageId=31984)，可以打开数据业务，打开后状态为高亮![](http://consumer.huawei.com/support/servlet/imageServlet?dlType=HtmlAreaImage&imageId=31985)。 \r\n\r\n ![](http://consumer.huawei.com/support/servlet/imageServlet?dlType=HtmlAreaImage&imageId=31986)",
  "faqTypeId": 138,
  "faqType": "网络与数据共享",
  "useful": 0,
  "unUseful": 4,
  "languageId": 2,
  "languageName": "zh_cn",
  "faqCode": "1682",
  "faqTypeCode": "Handsets-Network-Data-sharing",
  "isTop": "0",
  "moduleCode": "faq",
  "productId": null,
  "productCode": null,
  "postDate": 1397788265000,
  "seriesProductName": "H30-T10,H30-U10",
  "visitedTimes": 163,
  "isUsefulFlag": null,
  "score": 0,
  "times": 0,
  "imageList": null,
  "displayType": "text",
  "justView": "0",
  "fileName": null,
  "filePath": null,
  "imagePath": null,
  "imageName": null,
  "productIdList": null,
  "curPage": null,
  "pageSize": null,
  "siteCode": null,
  "statusFlag": "Publish",
  "returnCode": 0,
  "totalRows": null,
  "keywords": "荣耀3C （H30-T10&H30-U10）",
  "avgScore": 0.0,
  "createDate": null,
  "totalPages": null
}