{
  "type": null,
  "faqId": 11310,
  "title": "Mate2 (MT2-L05)  导航软件数据丢失如何处理？授权文件或激活码丢失如何处理？",
  "answer": " 如果高德导航软件数据丢失，建议连接上WIFI重新下载地图数据； \r\n\r\n 或者拷贝数据包到“内置存储卡”，然后点击“自动搜索导航数据”。",
  "faqTypeId": 142,
  "faqType": "位置服务与导航",
  "useful": 0,
  "unUseful": 0,
  "languageId": 2,
  "languageName": "zh_cn",
  "faqCode": "2070",
  "faqTypeCode": "Handsets-Location-Navigation",
  "isTop": "0",
  "moduleCode": "faq",
  "productId": null,
  "productCode": null,
  "postDate": 1398216651000,
  "seriesProductName": "MT2-L05",
  "visitedTimes": 18,
  "isUsefulFlag": null,
  "score": 0,
  "times": 0,
  "imageList": null,
  "displayType": "text",
  "justView": "0",
  "fileName": null,
  "filePath": null,
  "imagePath": null,
  "imageName": null,
  "productIdList": null,
  "curPage": null,
  "pageSize": null,
  "siteCode": null,
  "statusFlag": "Publish",
  "returnCode": 0,
  "totalRows": null,
  "keywords": "Mate2 (MT2-L05)",
  "avgScore": 0.0,
  "createDate": null,
  "totalPages": null
}