{
  "type": null,
  "faqId": 17213,
  "title": "荣耀畅玩手环(AF500)_在IOS应用的APP应用程序现在是否可以在苹果官方APP STORE下载？",
  "answer": "华为正在申请上线苹果APP store，等待苹果的审批，审批通过后，苹果用户即可在苹果APP store下载使用。\r\n\r\n且目前可以通过扫描包装盒或说明书后面的二维码下载IOS版APP，或者进这个地址下载[http://health.vmall.com/download/app/af500](http://health.vmall.com/download/app/af500)",
  "faqTypeId": null,
  "faqType": null,
  "useful": 0,
  "unUseful": 2,
  "languageId": 2,
  "languageName": "zh_cn",
  "faqCode": "9868",
  "faqTypeCode": null,
  "isTop": "0",
  "moduleCode": "faq",
  "productId": null,
  "productCode": null,
  "postDate": 1418267344000,
  "seriesProductName": "AF500",
  "visitedTimes": 568,
  "isUsefulFlag": null,
  "score": 3,
  "times": 1,
  "imageList": null,
  "displayType": "text",
  "justView": "0",
  "fileName": null,
  "filePath": null,
  "imagePath": null,
  "imageName": null,
  "productIdList": null,
  "curPage": null,
  "pageSize": null,
  "siteCode": null,
  "statusFlag": "Publish",
  "returnCode": 0,
  "totalRows": null,
  "keywords": "荣耀畅玩手环，AF500，IOS，APP，苹果，下载，APPSTORE",
  "avgScore": 3.0,
  "createDate": null,
  "totalPages": null
}