{
  "type": null,
  "faqId": 17221,
  "title": "荣耀畅玩4X(Che1-CL20)_卡1电信卡，卡2联通、移动，卡2为什么不能上3G/4G网络？",
  "answer": "荣耀畅玩4X支持的是双卡双待单通，并且卡1支持电信4G，根据电信4G技术限制，当卡1启用电信卡时，卡2只能驻留GSM。用户可以拔掉电信卡，让卡2上移动/联通的3G/4G。",
  "faqTypeId": 138,
  "faqType": "网络与数据共享",
  "useful": 13,
  "unUseful": 29,
  "languageId": 2,
  "languageName": "zh_cn",
  "faqCode": "9864",
  "faqTypeCode": "Handsets-Network-Data-sharing",
  "isTop": "0",
  "moduleCode": "faq",
  "productId": null,
  "productCode": null,
  "postDate": 1418264950000,
  "seriesProductName": "Cherry-CL10,Cherry-CL20",
  "visitedTimes": 3773,
  "isUsefulFlag": null,
  "score": 21,
  "times": 7,
  "imageList": null,
  "displayType": "text",
  "justView": "3",
  "fileName": null,
  "filePath": null,
  "imagePath": null,
  "imageName": null,
  "productIdList": null,
  "curPage": null,
  "pageSize": null,
  "siteCode": null,
  "statusFlag": "Publish",
  "returnCode": 0,
  "totalRows": null,
  "keywords": "荣耀畅玩4X，Che1-CL20，电信，上网，数据",
  "avgScore": 3.0,
  "createDate": null,
  "totalPages": null
}