{
  "type": null,
  "faqId": 17868,
  "title": "荣耀6Plus与HTC M8 ONE的差异？",
  "answer": "HTC两个摄像头的指标完全不一样，分为主次摄像头（为大小眼），顶部的副摄像头只有200W像素，视场角也不同，仅用来捕捉深度信息，并不能拍照。\r\n\r\n但是荣耀6 Plus的双摄像头两个摄像头均会参与成像。以及成像的合成中去。包含超分辨率成像、HDR照片、夜景等非常多的功能中。也这是我们可以支持光圈F0.95 - F16效果的原因。",
  "faqTypeId": 144,
  "faqType": "其他",
  "useful": 3,
  "unUseful": 3,
  "languageId": 2,
  "languageName": "zh_cn",
  "faqCode": "642",
  "faqTypeCode": "Handsets-Others",
  "isTop": "0",
  "moduleCode": "faq",
  "productId": null,
  "productCode": null,
  "postDate": 1420336303000,
  "seriesProductName": "Pine-TL10,Pine-TL20,Pine-UL00",
  "visitedTimes": 397,
  "isUsefulFlag": null,
  "score": 0,
  "times": 0,
  "imageList": null,
  "displayType": "text",
  "justView": "0",
  "fileName": null,
  "filePath": null,
  "imagePath": null,
  "imageName": null,
  "productIdList": null,
  "curPage": null,
  "pageSize": null,
  "siteCode": null,
  "statusFlag": "Publish",
  "returnCode": 0,
  "totalRows": null,
  "keywords": "荣耀6Plus,HTC M8 ONE,差异",
  "avgScore": 0.0,
  "createDate": null,
  "totalPages": null
}