{
  "type": null,
  "faqId": 18091,
  "title": "荣耀3 Emui3.0升级没有在线主题？",
  "answer": "没有在线主题是由于SD卡升级没有清除您数据，导致升级到EMUI3.0之后，应用程序的数据库还是1.6的版本，建议备份数据后，进入设置->备份与重置中，恢复出厂设置。",
  "faqTypeId": 143,
  "faqType": "系统功能与设置",
  "useful": 0,
  "unUseful": 0,
  "languageId": 2,
  "languageName": "zh_cn",
  "faqCode": "911",
  "faqTypeCode": "Handsets-System-Settings",
  "isTop": "0",
  "moduleCode": "faq",
  "productId": null,
  "productCode": null,
  "postDate": 1420601651000,
  "seriesProductName": "H30-L01,H30-L02",
  "visitedTimes": 102,
  "isUsefulFlag": null,
  "score": 0,
  "times": 0,
  "imageList": null,
  "displayType": "text",
  "justView": "2",
  "fileName": null,
  "filePath": null,
  "imagePath": null,
  "imageName": null,
  "productIdList": null,
  "curPage": null,
  "pageSize": null,
  "siteCode": null,
  "statusFlag": "Publish",
  "returnCode": 0,
  "totalRows": null,
  "keywords": "HN3,EMUI3.0,3.0,升级,主题",
  "avgScore": 0.0,
  "createDate": null,
  "totalPages": null
}