{
  "type": null,
  "faqId": 19284,
  "title": "荣耀畅玩4移动版更新了3.0图库只显示相机拍的照片不显示别的图？",
  "answer": " 图库显示图片，默认是按照时间轴的方式显示手机上拍出的照片，如果需要查看手机上所有的照片，请点击图库界面下方的列表按钮，切换到列表显示模式。 \r\n\n\n\n\n",
  "faqTypeId": 1086,
  "faqType": "相机与图库",
  "useful": 0,
  "unUseful": 0,
  "languageId": 2,
  "languageName": "zh_cn",
  "faqCode": "2384",
  "faqTypeCode": "Handsets-Camera-Gallery",
  "isTop": "0",
  "moduleCode": "faq",
  "productId": null,
  "productCode": null,
  "postDate": 1422340617000,
  "seriesProductName": "G621-TL00,G621-TL00M",
  "visitedTimes": 108,
  "isUsefulFlag": null,
  "score": 0,
  "times": 0,
  "imageList": null,
  "displayType": "text",
  "justView": "0",
  "fileName": null,
  "filePath": null,
  "imagePath": null,
  "imageName": null,
  "productIdList": null,
  "curPage": null,
  "pageSize": null,
  "siteCode": null,
  "statusFlag": "Publish",
  "returnCode": 0,
  "totalRows": null,
  "keywords": "荣耀畅玩4,移动版,相机,拍照,图片",
  "avgScore": 0.0,
  "createDate": null,
  "totalPages": null
}