{
  "type": null,
  "faqId": 19676,
  "title": "荣耀畅玩4移动版后台应用只能全部清除，不能单独关闭？",
  "answer": " 您好，按多任务键，在多任务界面将需要关闭想应用缩略图向上滑动即可单独关闭该应用。 \r\n\n\n\n\n",
  "faqTypeId": 139,
  "faqType": "应用程序管理",
  "useful": 0,
  "unUseful": 0,
  "languageId": 2,
  "languageName": "zh_cn",
  "faqCode": "2896",
  "faqTypeCode": "Handsets-Application-Management",
  "isTop": "0",
  "moduleCode": "faq",
  "productId": null,
  "productCode": null,
  "postDate": 1423274190000,
  "seriesProductName": "G621-TL00M",
  "visitedTimes": 79,
  "isUsefulFlag": null,
  "score": 0,
  "times": 0,
  "imageList": null,
  "displayType": "text",
  "justView": "0",
  "fileName": null,
  "filePath": null,
  "imagePath": null,
  "imageName": null,
  "productIdList": null,
  "curPage": null,
  "pageSize": null,
  "siteCode": null,
  "statusFlag": "Publish",
  "returnCode": 0,
  "totalRows": null,
  "keywords": "荣耀畅玩4移动版,后台应用,全部清除,单独关闭",
  "avgScore": 0.0,
  "createDate": null,
  "totalPages": null
}