{
  "type": null,
  "faqId": 19957,
  "title": "如何查看录音文件的保存路径？",
  "answer": " ![](http://consumer.huawei.com/support/servlet/imageServlet?dlType=HtmlAreaImage&imageId=66669)\r\n\r\n 部分产品不支持此功能，请以实物为准。 \r\n\r\n 1. 在主屏幕界面点击 “实用工具 > 录音机 > ![](http://consumer.huawei.com/support/servlet/imageServlet?dlType=HtmlAreaImage&imageId=66670)” 进入录音文件列表。 \r\n\r\n 1. 点击文件右侧的 “![](http://consumer.huawei.com/support/servlet/imageServlet?dlType=HtmlAreaImage&imageId=66671)”，在录音文件的“详细信息”界面可以找到该文件的存储位置。 \r\n\r\n [<a name=\"gen-id1.3.11.2.2.2.3.1\"></a>]()![](http://consumer.huawei.com/support/servlet/imageServlet?dlType=HtmlAreaImage&imageId=66672)\r\n\r\n ![](http://consumer.huawei.com/support/servlet/imageServlet?dlType=HtmlAreaImage&imageId=66673)\r\n\r\n 所有图片仅供参考，具体操作请以实际界面为准。 \r\n\n\n\n\n",
  "faqTypeId": 167,
  "faqType": "相机与图库",
  "useful": 0,
  "unUseful": 0,
  "languageId": 2,
  "languageName": "zh_cn",
  "faqCode": "3378",
  "faqTypeCode": "Tablet-Camera-Picture",
  "isTop": "0",
  "moduleCode": "faq",
  "productId": null,
  "productCode": null,
  "postDate": 1425286522000,
  "seriesProductName": "T1-821w,T1-823L",
  "visitedTimes": 12,
  "isUsefulFlag": null,
  "score": 0,
  "times": 0,
  "imageList": null,
  "displayType": "text",
  "justView": "0",
  "fileName": null,
  "filePath": null,
  "imagePath": null,
  "imageName": null,
  "productIdList": null,
  "curPage": null,
  "pageSize": null,
  "siteCode": null,
  "statusFlag": "Publish",
  "returnCode": 0,
  "totalRows": null,
  "keywords": "录音,保存,存储位置,存储路径",
  "avgScore": 0.0,
  "createDate": null,
  "totalPages": null
}