{
  "type": null,
  "faqId": 20086,
  "title": "荣耀6Plus SD卡无法识别？",
  "answer": " 1)建议您先拔出SD卡，手机在线升级到最新版本后尝试； \r\n\r\n 2)仍然无法识别的，请备份SD卡的数据后格式化尝试； \r\n\r\n 3)仍然无法识别的，请换其他厂家或者其他容量的SD卡尝试； \r\n\r\n 4)仍然无法识别的，请换卡托尝试，或者去网点检测。 \r\n\n\n\n\n",
  "faqTypeId": 144,
  "faqType": "其他",
  "useful": 0,
  "unUseful": 0,
  "languageId": 2,
  "languageName": "zh_cn",
  "faqCode": "3566",
  "faqTypeCode": "Handsets-Others",
  "isTop": "0",
  "moduleCode": "faq",
  "productId": null,
  "productCode": null,
  "postDate": 1425627131000,
  "seriesProductName": "Pine-CL00,Pine-TL00M,Pine-TL10,Pine-TL20,Pine-UL00",
  "visitedTimes": 957,
  "isUsefulFlag": null,
  "score": 0,
  "times": 0,
  "imageList": null,
  "displayType": "text",
  "justView": "0",
  "fileName": null,
  "filePath": null,
  "imagePath": null,
  "imageName": null,
  "productIdList": null,
  "curPage": null,
  "pageSize": null,
  "siteCode": null,
  "statusFlag": "Publish",
  "returnCode": 0,
  "totalRows": null,
  "keywords": "荣耀6Plus,SD,无法识别",
  "avgScore": 0.0,
  "createDate": null,
  "totalPages": null
}