{
  "type": null,
  "faqId": 21879,
  "title": "Wi-Fi 中继、智联桥接模式下，如何切回路由模式？",
  "answer": " 恢复出厂设置。这是最简单的方式。 \r\n\n\n\n\n",
  "faqTypeId": null,
  "faqType": null,
  "useful": 0,
  "unUseful": 0,
  "languageId": 2,
  "languageName": "zh_cn",
  "faqCode": "5619",
  "faqTypeCode": null,
  "isTop": "0",
  "moduleCode": "faq",
  "productId": null,
  "productCode": null,
  "postDate": 1428048448000,
  "seriesProductName": "WS831-10",
  "visitedTimes": 64,
  "isUsefulFlag": null,
  "score": 3,
  "times": 1,
  "imageList": null,
  "displayType": "text",
  "justView": "0",
  "fileName": null,
  "filePath": null,
  "imagePath": null,
  "imageName": null,
  "productIdList": null,
  "curPage": null,
  "pageSize": null,
  "siteCode": null,
  "statusFlag": "Publish",
  "returnCode": 0,
  "totalRows": null,
  "keywords": null,
  "avgScore": 3.0,
  "createDate": null,
  "totalPages": null
}