{
  "type": null,
  "faqId": 33070,
  "title": "提示内存不足怎么处理？",
  "answer": "# 提示内存不足怎么处理？\r\n\r\n1. 将大文件移动至SD卡中保存。\r\n\r\n对于支持外置 microSD 卡的手机，若插入了 microSD 卡，建议将手机内部存储中的图片、音乐、视频等文件移至 microSD 卡中。\r\n\r\n2. 清理存储空间。\r\n\r\n可以使用“手机管家”或“文件管理”中的清理功能清理垃圾文件。\r\n\r\nEMUI3.1：\r\n\r\n文件管理->清理文件->勾选需要清理的数据->一键清理\r\n\r\n手机管家->空间清理->勾选需要清理的数据->一键清理\r\n\r\nEMUI4.0：\r\n\r\n文件管理->清理文件->勾选需要清理的数据->一键清理\r\n\r\n手机管家->清理加速->勾选需要清理的数据->一键清理\r\n\r\n根据屏幕提示清理手机。\r\n\r\n若尝试以上方法后，仍然提示内存不足，建议备份重要数据后将手机恢复出厂设置。\r\n<script language=\"JavaScript\"></script>",
  "faqTypeId": 140,
  "faqType": "存储与文件管理",
  "useful": 0,
  "unUseful": 0,
  "languageId": 2,
  "languageName": "zh_cn",
  "faqCode": "zh-cn_topic_0031761882",
  "faqTypeCode": "Handsets-Storage-File-management",
  "isTop": "0",
  "moduleCode": "faq",
  "productId": null,
  "productCode": null,
  "postDate": 1436748496000,
  "seriesProductName": "ALE-CL00,ALE-TL00,ALE-UL00,ATH-CL00,ATH-TL00,ATH-TL00H,ATH-UL00,CRR-CL00,CRR-CL20,CRR-CL20a,CRR-UL00,CRR-UL20,CRR-UL20a,GRA-CL00,GRA-CL10,GRA-TL00,GRA-UL00,GRA-UL10,Jazz-CL00,Jazz-TL00,Jazz-TL10,Jazz-TL10A,Jazz-TL20,Jazz-UL00,KIW-AL10,KIW-CL00,KIW-TL00,KIW-TL00H,KIW-UL00,NXT-AL10A,NXT-AL10B,NXT-AL10C,PLK-AL10,PLK-CL00,PLK-TL00,PLK-TL01H,PLK-TL11H,PLK-UL00,RIO-AL00,RIO-CL00,RIO-TL00,RIO-UL00,RIO-UL10",
  "visitedTimes": 164,
  "isUsefulFlag": null,
  "score": 0,
  "times": 0,
  "imageList": null,
  "displayType": "text",
  "justView": "0",
  "fileName": null,
  "filePath": null,
  "imagePath": null,
  "imageName": null,
  "productIdList": null,
  "curPage": null,
  "pageSize": null,
  "siteCode": null,
  "statusFlag": "Publish",
  "returnCode": 0,
  "totalRows": null,
  "keywords": "内存不足",
  "avgScore": 0.0,
  "createDate": null,
  "totalPages": null
}