{
  "type": null,
  "faqId": 33185,
  "title": "手机突然发送了一条短信给不知名的号码，怎么回事？",
  "answer": " 非手机出厂预置的第三方应用程序如果在后台发短信，会被手机记录下来，可以在短信界面中看到。这样的显示方式提醒您安装了可疑的第三方应用程序。 \r\n\n\n\n\n",
  "faqTypeId": 136,
  "faqType": "信息与邮件",
  "useful": 0,
  "unUseful": 0,
  "languageId": 2,
  "languageName": "zh_cn",
  "faqCode": "7887",
  "faqTypeCode": "Handsets-SMS-Email",
  "isTop": "0",
  "moduleCode": "faq",
  "productId": null,
  "productCode": null,
  "postDate": 1436748524000,
  "seriesProductName": "PLK-AL10,PLK-CL00,PLK-TL00,PLK-TL01H,PLK-UL00",
  "visitedTimes": 9,
  "isUsefulFlag": null,
  "score": 0,
  "times": 0,
  "imageList": null,
  "displayType": "text",
  "justView": "0",
  "fileName": null,
  "filePath": null,
  "imagePath": null,
  "imageName": null,
  "productIdList": null,
  "curPage": null,
  "pageSize": null,
  "siteCode": null,
  "statusFlag": "Publish",
  "returnCode": 0,
  "totalRows": null,
  "keywords": "短信,发送,后台程序",
  "avgScore": 0.0,
  "createDate": null,
  "totalPages": null
}