{
  "type": null,
  "faqId": 33598,
  "title": "计步器不计数？",
  "answer": " 计步器在使用前，需要先清空一次应用数据。 \r\n\r\n 设置方式：设置 -应用管理，在“全部”列表下，找到华为运动健康，点击进入应用程序信息，然后点击清除数据。 \r\n\n\n\n\n",
  "faqTypeId": 139,
  "faqType": "应用程序管理",
  "useful": 0,
  "unUseful": 0,
  "languageId": 2,
  "languageName": "zh_cn",
  "faqCode": "8318",
  "faqTypeCode": "Handsets-Application-Management",
  "isTop": "0",
  "moduleCode": "faq",
  "productId": null,
  "productCode": null,
  "postDate": 1436748666000,
  "seriesProductName": "PLK-AL10,PLK-CL00,PLK-TL00,PLK-TL01H,PLK-UL00",
  "visitedTimes": 37,
  "isUsefulFlag": null,
  "score": 0,
  "times": 0,
  "imageList": null,
  "displayType": "text",
  "justView": "0",
  "fileName": null,
  "filePath": null,
  "imagePath": null,
  "imageName": null,
  "productIdList": null,
  "curPage": null,
  "pageSize": null,
  "siteCode": null,
  "statusFlag": "Publish",
  "returnCode": 0,
  "totalRows": null,
  "keywords": "计步器,计数",
  "avgScore": 0.0,
  "createDate": null,
  "totalPages": null
}