{
  "type": null,
  "faqId": 44098,
  "title": "为什么手机将照片进行不断放大后有模糊的感觉？",
  "answer": " 为了便于您将图像的清晰程度发挥到最大，给您的图片放大空间很大，您可以放大到超过一个屏幕像素点对应一个图像像素点。因此在放大到一定程度后继续放大时会出现一个照片像素对应多个显示屏像素的情况， 从而使人有马赛克或者模糊的感觉。是正常现象。 \r\n\n\n\n\n",
  "faqTypeId": 1086,
  "faqType": "相机与图库",
  "useful": 0,
  "unUseful": 0,
  "languageId": 2,
  "languageName": "zh_cn",
  "faqCode": "9598",
  "faqTypeCode": "Handsets-Camera-Gallery",
  "isTop": "0",
  "moduleCode": "faq",
  "productId": null,
  "productCode": null,
  "postDate": 1442400089000,
  "seriesProductName": "CRR-CL10,CRR-TL10,CRR-UL10",
  "visitedTimes": 1,
  "isUsefulFlag": null,
  "score": 0,
  "times": 0,
  "imageList": null,
  "displayType": "text",
  "justView": "0",
  "fileName": null,
  "filePath": null,
  "imagePath": null,
  "imageName": null,
  "productIdList": null,
  "curPage": null,
  "pageSize": null,
  "siteCode": null,
  "statusFlag": "Publish",
  "returnCode": 0,
  "totalRows": null,
  "keywords": "照片,放大,模糊,像素",
  "avgScore": 0.0,
  "createDate": null,
  "totalPages": null
}