{
  "type": null,
  "faqId": 46158,
  "title": "闪光灯概率性不亮是什么情况？",
  "answer": " 为了保证用户的人身安全，不出现烫伤的场景，在长时间录像拍照后，手机会进入了热保护。 \r\n\r\n\n\n\n\n",
  "faqTypeId": 1086,
  "faqType": "相机与图库",
  "useful": 0,
  "unUseful": 0,
  "languageId": 2,
  "languageName": "zh_cn",
  "faqCode": "1938",
  "faqTypeCode": "Handsets-Camera-Gallery",
  "isTop": "0",
  "moduleCode": "faq",
  "productId": null,
  "productCode": null,
  "postDate": 1444376112000,
  "seriesProductName": "",
  "visitedTimes": 16,
  "isUsefulFlag": null,
  "score": 0,
  "times": 0,
  "imageList": null,
  "displayType": "text",
  "justView": "0",
  "fileName": null,
  "filePath": null,
  "imagePath": null,
  "imageName": null,
  "productIdList": null,
  "curPage": null,
  "pageSize": null,
  "siteCode": null,
  "statusFlag": "Publish",
  "returnCode": 0,
  "totalRows": null,
  "keywords": "闪光灯,不亮",
  "avgScore": 0.0,
  "createDate": null,
  "totalPages": null
}