{
  "type": null,
  "faqId": 47406,
  "title": "如何查询华为手机服务网点？",
  "answer": " 进入[服务中心](http://consumer.huawei.com/cn/support/service-center/index.htm%22 \\o %22 )查询全国服务网点， 或关注华为终端官方微信平台（微信号：huaweizhongduan），点击“自助服务”>“服务中心查询”根据屏幕提示查询华为手机的服务网点。 \r\n\n\n\n\n",
  "faqTypeId": 144,
  "faqType": "其他",
  "useful": 0,
  "unUseful": 1,
  "languageId": 2,
  "languageName": "zh_cn",
  "faqCode": "2990",
  "faqTypeCode": "Handsets-Others",
  "isTop": "0",
  "moduleCode": "faq",
  "productId": null,
  "productCode": null,
  "postDate": 1445219313000,
  "seriesProductName": "TIT-AL00,TIT-CL10,TIT-TL00",
  "visitedTimes": 281,
  "isUsefulFlag": null,
  "score": 0,
  "times": 0,
  "imageList": null,
  "displayType": "text",
  "justView": "0",
  "fileName": null,
  "filePath": null,
  "imagePath": null,
  "imageName": null,
  "productIdList": null,
  "curPage": null,
  "pageSize": null,
  "siteCode": null,
  "statusFlag": "Publish",
  "returnCode": 0,
  "totalRows": null,
  "keywords": "查询网点",
  "avgScore": 0.0,
  "createDate": null,
  "totalPages": null
}