{
  "type": null,
  "faqId": 8783,
  "title": "荣耀3X（G750-T00）短信转发/群发与保存草稿的方法",
  "answer": "短信转发：会话模式下，读信息界面，长按需要转发的某一条短信，选择转发，转发给指定联系人。  \r\n\n短信群发：新建一条短信，点击右上角加号图标，进入添加联系人界面，选择需要添加的联系人，点击选择，群发短信到选择的联系人。  \r\n\n保存草稿：新建一条信息，输入收件人与信息内容后，点击手机后退键即可自动保存该会话的草稿；",
  "faqTypeId": 136,
  "faqType": "信息与邮件",
  "useful": 0,
  "unUseful": 0,
  "languageId": 2,
  "languageName": "zh_cn",
  "faqCode": "9340",
  "faqTypeCode": "Handsets-SMS-Email",
  "isTop": "0",
  "moduleCode": "faq",
  "productId": null,
  "productCode": null,
  "postDate": 1396075634000,
  "seriesProductName": "G750-T00",
  "visitedTimes": 56,
  "isUsefulFlag": null,
  "score": 0,
  "times": 0,
  "imageList": null,
  "displayType": "text",
  "justView": "0",
  "fileName": null,
  "filePath": null,
  "imagePath": null,
  "imageName": null,
  "productIdList": null,
  "curPage": null,
  "pageSize": null,
  "siteCode": null,
  "statusFlag": "Publish",
  "returnCode": 0,
  "totalRows": null,
  "keywords": null,
  "avgScore": 0.0,
  "createDate": null,
  "totalPages": null
}