{
  "type": null,
  "faqId": 34038,
  "title": " Why can't my phone be discovered by other Bluetooth devices?",
  "answer": " Bluetooth has been turned off on your phone. \r\n\r\n Solution 1: Go to Settings and turn on Bluetooth. \r\n\r\n ![](http://consumer.huawei.com/support/servlet/imageServlet?dlType=HtmlAreaImage&imageId=109353)![](http://consumer.huawei.com/support/servlet/imageServlet?dlType=HtmlAreaImage&imageId=109354)![](http://consumer.huawei.com/support/servlet/imageServlet?dlType=HtmlAreaImage&imageId=109355)\r\n\r\n Solution 2: Turn on Bluetooth from the notification panel. \r\n\r\n ![](http://consumer.huawei.com/support/servlet/imageServlet?dlType=HtmlAreaImage&imageId=109356)![](http://consumer.huawei.com/support/servlet/imageServlet?dlType=HtmlAreaImage&imageId=109357)\r\n\r\n Bluetooth is turned on, but your phone is not set to be visible to other devices. \r\n\r\n Solution: Go to Settings and touch Bluetooth > Visibility. \r\n\r\n ![](http://consumer.huawei.com/support/servlet/imageServlet?dlType=HtmlAreaImage&imageId=109358)\r\n\r\n The Bluetooth detection has timed out. \r\n\r\n Solution 1: Touch Settings > Bluetooth, turn off Visibility and turn it back on to recount the detection time. (Refer to the preceding figure.) \r\n\r\n [Touch ![](http://consumer.huawei.com/support/servlet/imageServlet?dlType=HtmlAreaImage&imageId=109359) > Visibility timeout and set a longer timeout period.]() \r\n\n\n\n\n",
  "faqTypeId": null,
  "faqType": null,
  "useful": 0,
  "unUseful": 0,
  "languageId": 244,
  "languageName": "mm",
  "faqCode": "8738",
  "faqTypeCode": null,
  "isTop": "0",
  "moduleCode": "faq",
  "productId": null,
  "productCode": null,
  "postDate": 1436779650000,
  "seriesProductName": "CHC-U01",
  "visitedTimes": 1,
  "isUsefulFlag": null,
  "score": 0,
  "times": 0,
  "imageList": null,
  "displayType": "text",
  "justView": "0",
  "fileName": null,
  "filePath": null,
  "imagePath": null,
  "imageName": null,
  "productIdList": null,
  "curPage": null,
  "pageSize": null,
  "siteCode": null,
  "statusFlag": "Publish",
  "returnCode": 0,
  "totalRows": null,
  "keywords": "CHC-U01,G play mini",
  "avgScore": 0.0,
  "createDate": null,
  "totalPages": null
}