{
  "type": null,
  "faqId": 34458,
  "title": " Mailbox Setting",
  "answer": "1Adding Email Accounts \r\n\r\n Enter the home menu > Email. The login account consists of manual setting and auto setting. \r\n\r\n - Manual setup: \r\n\r\n2Account Settings interface > Enter the account number and password. \r\n\r\n3Click Manual setup. \r\n\r\n4Click POP3 to enter the incoming server-setting interface. \r\n\r\n5Click Next to enter the outgoing server-setting interface. \r\n\r\n6Click Next to enter the Email reception-setting screen, and select the Inbox check frequency. \r\n\r\n7Click Next to enter the Email interface and create a name and your name for the account. \r\n\r\n8Click Next to complete the login and enter the Inbox interface. \r\n\r\n ![](http://consumer.huawei.com/support/servlet/imageServlet?dlType=HtmlAreaImage&imageId=109990) ![](http://consumer.huawei.com/support/servlet/imageServlet?dlType=HtmlAreaImage&imageId=109991)\r\n\r\n ![](http://consumer.huawei.com/support/servlet/imageServlet?dlType=HtmlAreaImage&imageId=109992) ![](http://consumer.huawei.com/support/servlet/imageServlet?dlType=HtmlAreaImage&imageId=109993)\r\n\r\n ![](http://consumer.huawei.com/support/servlet/imageServlet?dlType=HtmlAreaImage&imageId=109994) ![](http://consumer.huawei.com/support/servlet/imageServlet?dlType=HtmlAreaImage&imageId=109995)\r\n\r\n - Auto Setting (Auto Setting requires parameters of the Email of this type to be set in the phone): \r\n\r\n 1. Account Settings interface > Input the account number and password. \r\n\r\n 2. Click Next. \r\n\r\n 3. Click Next to enter the Email reception-setting screen, and select the Inbox check frequency. \r\n\r\n 4. Click Next to enter the Email interface and create a name and your name for the account. \r\n\r\n 5. Click Next to complete the login and enter the inbox interface. \r\n\r\n ![](http://consumer.huawei.com/support/servlet/imageServlet?dlType=HtmlAreaImage&imageId=109996) ![](http://consumer.huawei.com/support/servlet/imageServlet?dlType=HtmlAreaImage&imageId=109997)\r\n\r\n ![](http://consumer.huawei.com/support/servlet/imageServlet?dlType=HtmlAreaImage&imageId=109998)\r\n\r\n For non-preset Email accounts and the setting of the login process, users can log in to the Email service provider's website to search. \r\n\r\n6Sending Emails \r\n\r\n In the Inbox screen, click ![](http://consumer.huawei.com/support/servlet/imageServlet?dlType=HtmlAreaImage&imageId=109999) to enter the Write Email interface, edit the Recipient, Subject, Content, and then click Send Email. \r\n\r\n7View and delete Email \r\n\r\n In the Inbox interface, click mail to view the message; Click ![](http://consumer.huawei.com/support/servlet/imageServlet?dlType=HtmlAreaImage&imageId=110000) to delete the message. \r\n\r\n8Delete Email Account \r\n\r\n Enter Email, click ![](http://consumer.huawei.com/support/servlet/imageServlet?dlType=HtmlAreaImage&imageId=110001) > Settings, click the account you want to delete, and slide to the bottom to select Delete account. \r\n\r\n\n\n\n\n",
  "faqTypeId": null,
  "faqType": null,
  "useful": 0,
  "unUseful": 0,
  "languageId": 244,
  "languageName": "mm",
  "faqCode": "9218",
  "faqTypeCode": null,
  "isTop": "0",
  "moduleCode": "faq",
  "productId": null,
  "productCode": null,
  "postDate": 1436866798000,
  "seriesProductName": "Y625-U32",
  "visitedTimes": 1,
  "isUsefulFlag": null,
  "score": 0,
  "times": 0,
  "imageList": null,
  "displayType": "text",
  "justView": "0",
  "fileName": null,
  "filePath": null,
  "imagePath": null,
  "imageName": null,
  "productIdList": null,
  "curPage": null,
  "pageSize": null,
  "siteCode": null,
  "statusFlag": "Publish",
  "returnCode": 0,
  "totalRows": null,
  "keywords": "Y625-U32, Ascend Y25",
  "avgScore": 0.0,
  "createDate": null,
  "totalPages": null
}