{
  "type": null,
  "faqId": 35945,
  "title": " How do I save a web page for offline reading?",
  "answer": " Open a web page. Touch the menu key. From the displayed option menu, choose Save for offline reading. \r\n\r\n ![](http://consumer.huawei.com/support/servlet/imageServlet?dlType=HtmlAreaImage&imageId=112863)![](http://consumer.huawei.com/support/servlet/imageServlet?dlType=HtmlAreaImage&imageId=112864)\r\n\r\n\n\n\n\n",
  "faqTypeId": null,
  "faqType": null,
  "useful": 0,
  "unUseful": 0,
  "languageId": 244,
  "languageName": "mm",
  "faqCode": "785",
  "faqTypeCode": null,
  "isTop": "0",
  "moduleCode": "faq",
  "productId": null,
  "productCode": null,
  "postDate": 1437644525000,
  "seriesProductName": "Y330-U11",
  "visitedTimes": 1,
  "isUsefulFlag": null,
  "score": 0,
  "times": 0,
  "imageList": null,
  "displayType": "text",
  "justView": "0",
  "fileName": null,
  "filePath": null,
  "imagePath": null,
  "imageName": null,
  "productIdList": null,
  "curPage": null,
  "pageSize": null,
  "siteCode": null,
  "statusFlag": "Publish",
  "returnCode": 0,
  "totalRows": null,
  "keywords": "Ascend Y330 (Y330-U11)",
  "avgScore": 0.0,
  "createDate": null,
  "totalPages": null
}